odoo9_addon_stock_scrap-9.0.1.0.0.99.dev4-py3.8-nspkg.pth
odoo_addons/stock_scrap/README.rst
odoo_addons/stock_scrap/__init__.py
odoo_addons/stock_scrap/__openerp__.py
odoo_addons/stock_scrap/i18n/de.po
odoo_addons/stock_scrap/i18n/es.po
odoo_addons/stock_scrap/i18n/fr.po
odoo_addons/stock_scrap/i18n/it.po
odoo_addons/stock_scrap/i18n/sl.po
odoo_addons/stock_scrap/i18n/stock_scrap.pot
odoo_addons/stock_scrap/models/__init__.py
odoo_addons/stock_scrap/models/stock_scrap.py
odoo_addons/stock_scrap/security/ir.model.access.csv
odoo_addons/stock_scrap/static/description/icon.png
odoo_addons/stock_scrap/tests/__init__.py
odoo_addons/stock_scrap/tests/test_stock_scrap.py
odoo_addons/stock_scrap/views/stock_scrap_view.xml
odoo9_addon_stock_scrap-9.0.1.0.0.99.dev4.dist-info/METADATA
odoo9_addon_stock_scrap-9.0.1.0.0.99.dev4.dist-info/WHEEL
odoo9_addon_stock_scrap-9.0.1.0.0.99.dev4.dist-info/namespace_packages.txt
odoo9_addon_stock_scrap-9.0.1.0.0.99.dev4.dist-info/top_level.txt
odoo9_addon_stock_scrap-9.0.1.0.0.99.dev4.dist-info/RECORD
